{
  "pmid": "18039989",
  "title": "Prospective study of dietary carbohydrates, glycemic index, glycemic load, and incidence of type 2 diabetes mellitus in middle-aged Chinese women",
  "authors": "Villegas R, Liu S, Gao YT, Yang G, Li H, Zheng W, Shu XO",
  "year": 2007,
  "journal": "Arch Intern Med",
  "category": "epidemiology",
  "abstract": "中国中年女性膳食碳水化合物、GI、GL与2型糖尿病发病率的前瞻性研究。",
  "added_date": "2026-03-06T14:38:17.650182",
  "urls": {
    "pubmed": "https://pubmed.ncbi.nlm.nih.gov/18039989/",
    "pmc": "https://www.ncbi.nlm.nih.gov/pmc/articles/PMC18039989/"
  }
}